mathphys/VERSION
mathphys/__init__.py
mathphys/base_units.py
mathphys/beam_optics.py
mathphys/constants.py
mathphys/functions.py
mathphys/imgproc.py
mathphys/units.py
mathphys-2.11.0.dist-info/licenses/LICENSE
mathphys-2.11.0.dist-info/METADATA
mathphys-2.11.0.dist-info/WHEEL
mathphys-2.11.0.dist-info/top_level.txt
mathphys-2.11.0.dist-info/RECORD
