Metadata-Version: 2.4
Name: mathphys
Version: 2.11.0
Summary: LNLS Math and Physics Utilities
Home-page: https://github.com/lnls-fac/mathphys
Download-URL: https://github.com/lnls-fac/mathphys
Author: lnls-fac
Author-email: xresende@gmail.com
Maintainer-email: Ana Oliveira <ana.clara@lnls.br>, Ximenes Resende <xresende@gmail.com>, "Fernando H. de Sá" <fernandohds564@gmail.com>, Murilo Barbosa Alves <alvesb.murilo@gmail.com>
License-Expression: MIT
Project-URL: Homepage, https://github.com/lnls-fac/mathphys
Project-URL: Download, https://github.com/lnls-fac/mathphys
Project-URL: Repository, https://github.com/lnls-fac/mathphys.git
Project-URL: Issues, https://github.com/lnls-fac/mathphys/issues
Classifier: Intended Audience :: Science/Research
Classifier: Programming Language :: Python
Classifier: Topic :: Scientific/Engineering
Requires-Python: >=3.4
License-File: LICENSE
Requires-Dist: importlib-metadata
Requires-Dist: numpy<=1.23,>=1.18
Requires-Dist: matplotlib>=3.1.2
Requires-Dist: h5py>=3.1.0
Dynamic: author-email
Dynamic: download-url
Dynamic: home-page
Dynamic: license-file
Dynamic: requires-python
